app_scraper/__init__.py
app_scraper/api.py
app_scraper/constants.py
app_scraper/scraper.py
app_scraper/settings.py
app_scraper/utils.py
app_scraper-0.0.5.dist-info/LICENSE
app_scraper-0.0.5.dist-info/METADATA
app_scraper-0.0.5.dist-info/WHEEL
app_scraper-0.0.5.dist-info/top_level.txt
app_scraper-0.0.5.dist-info/RECORD
