Metadata-Version: 2.1
Name: app-scraper
Version: 0.0.5
Summary: A small example package
Home-page: https://github.com/filbert-c/app-scraper
Author: filbert
Author-email: filbert.cheong@gmail.com
License: UNKNOWN
Platform: UNKNOWN
Classifier: Programming Language :: Python :: 3
Classifier: License :: OSI Approved :: MIT License
Classifier: Operating System :: OS Independent
Requires-Python: >=3.6
